pydxdiag/DxdiagParser.py
pydxdiag/__init__.py
pydxdiag/functions/EnvPowerInformation.py
pydxdiag/functions/Filter.py
pydxdiag/functions/LogicalDisk.py
pydxdiag/functions/SystemInformation.py
pydxdiag/functions/WER.py
pydxdiag/functions/__init__.py
pydxdiag/functions/device/DirectInputDevice.py
pydxdiag/functions/device/DisplayDevice.py
pydxdiag/functions/device/InputRelatedDevice.py
pydxdiag/functions/device/SoundCaptureDevice.py
pydxdiag/functions/device/SoundDevice.py
pydxdiag/functions/device/SystemDevice.py
pydxdiag/functions/device/VideoCaptureDevice.py
pydxdiag/functions/device/__init__.py
pydxdiag/functions/sz/__init__.py
pydxdiag/functions/sz/szByteStreamHandler.py
pydxdiag/functions/sz/szEnabledHardwareMFT.py
pydxdiag/functions/sz/szMFFileVersions.py
pydxdiag/functions/sz/szMFTs.py
pydxdiag/functions/sz/szPreferredMFT.py
pydxdiag/functions/sz/szSchemeHandlers.py
pydxdiag/schema/DirectXDebugLevels.py
pydxdiag/schema/DxDiagNotes.py
pydxdiag/schema/EnvPowerInformation.py
pydxdiag/schema/Filter.py
pydxdiag/schema/LogicalDisk.py
pydxdiag/schema/SystemInformation.py
pydxdiag/schema/WER.py
pydxdiag/schema/__init__.py
pydxdiag/schema/device/DirectInputDevice.py
pydxdiag/schema/device/DisplayDevice.py
pydxdiag/schema/device/InputRelatedDevice.py
pydxdiag/schema/device/SoundCaptureDevice.py
pydxdiag/schema/device/SoundDevice.py
pydxdiag/schema/device/SystemDevice.py
pydxdiag/schema/device/VideoCaptureDevice.py
pydxdiag/schema/device/__init__.py
pydxdiag/schema/sz/__init__.py
pydxdiag/schema/sz/szBytesStreamHandler.py
pydxdiag/schema/sz/szEnableHardwareMFT.py
pydxdiag/schema/sz/szMFFileVersion.py
pydxdiag/schema/sz/szMFT.py
pydxdiag/schema/sz/szPreferredMFT.py
pydxdiag/schema/sz/szSchemeHandlers.py
pydxdiag-0.2.1.dist-info/METADATA
pydxdiag-0.2.1.dist-info/WHEEL
pydxdiag-0.2.1.dist-info/top_level.txt
pydxdiag-0.2.1.dist-info/RECORD
