Metadata-Version: 2.1
Name: pydxdiag
Version: 0.2.1
Summary: A python library for parsing dxdiag output
Home-page: https://github.com/ElinLiu0/pydxdiag
Author: Elin
Author-email: 982467922@qq.com
Classifier: Programming Language :: Python
Classifier: Programming Language :: Python :: 3
Requires-Python: >=3.10
Requires-Dist: pydantic
Requires-Dist: beautifulsoup4
Requires-Dist: lxml
